README
setup.py
dm/__init__.py
dm.profile.egg-info/PKG-INFO
dm.profile.egg-info/SOURCES.txt
dm.profile.egg-info/dependency_links.txt
dm.profile.egg-info/namespace_packages.txt
dm.profile.egg-info/top_level.txt
dm.profile.egg-info/zip-safe
dm/profile/LICENSE.txt
dm/profile/README.txt
dm/profile/VERSION.txt
dm/profile/__init__.py
dm/profile/dmprofile.py
dm/profile/dmstats.py
