Metadata-Version: 1.0
Name: dm.profile
Version: 1.0
Summary: Easier readable profile statistics -- especially for caller and callee analysis
Home-page: http://pypi.python.org/pypi/dm.profile
Author: Dieter Maurer
Author-email: dieter@handshake.de
License: BSD (see "dm/profile/LICENSE.txt", for details)
Keywords: profiling statistics caller callee analysis
Platform: UNKNOWN
Classifier: Development Status :: 5 - Production/Stable
Classifier: Intended Audience :: Developers
Classifier: License :: OSI Approved :: BSD License
Classifier: Operating System :: OS Independent
Classifier: Programming Language :: Python
Classifier: Topic :: Software Development
